perdict/__init__.py
perdict/perdict.py
perdict/utils.py
perdict-0.0.1.dist-info/LICENSE
perdict-0.0.1.dist-info/METADATA
perdict-0.0.1.dist-info/WHEEL
perdict-0.0.1.dist-info/top_level.txt
perdict-0.0.1.dist-info/RECORD
