Metadata-Version: 2.1
Name: perdict
Version: 0.0.1
Summary: Super simple Persistent dictionary.
Home-page: https://github.com/disentcorp/perdict
Author: Batu Davaademberel
Author-email: batu@disent.com
License: Apache Software License
Classifier: Development Status :: 3 - Alpha
Classifier: Intended Audience :: Science/Research
Classifier: Intended Audience :: Developers
Classifier: Programming Language :: Python
Classifier: Programming Language :: Python :: 3
Classifier: Programming Language :: Python :: 3.7
Classifier: Programming Language :: Python :: 3.8
Classifier: Programming Language :: Python :: 3.9
Classifier: Programming Language :: Python :: 3.10
Classifier: Programming Language :: Python :: 3.11
Classifier: Programming Language :: Python :: 3.12
Classifier: Programming Language :: Python :: 3 :: Only
Classifier: Topic :: Software Development
Classifier: Topic :: Scientific/Engineering
Classifier: License :: OSI Approved :: Apache Software License
Classifier: Topic :: Utilities
Classifier: Operating System :: Unix
Requires-Python: >=3.7
License-File: LICENSE
